stringprocess/__init__.py
stringprocess/processing.py
stringprocess/processors/__init__.py
stringprocess/processors/converters.py
stringprocess/processors/registry.py
stringprocess/processors/removers.py
stringprocess/processors/validators.py
stringprocess-1.0.dist-info/LICENSE
stringprocess-1.0.dist-info/METADATA
stringprocess-1.0.dist-info/WHEEL
stringprocess-1.0.dist-info/top_level.txt
stringprocess-1.0.dist-info/zip-safe
stringprocess-1.0.dist-info/RECORD
