Metadata-Version: 2.1
Name: stringprocess
Version: 1.0
Summary: string formatting, normalization and validation utilities
Home-page: https://github.com/koodaamo/stringprocess
Author: Petri Savolainen
Author-email: petri@koodaamo.fi
License: GPLv3
Keywords: string,transform,validation,normalization
Platform: UNKNOWN
Classifier: License :: OSI Approved :: GNU General Public License v3 (GPLv3)
Classifier: Programming Language :: Python :: 3
License-File: LICENSE
Requires-Dist: cleanco
Requires-Dist: unidecode
